{
	"metadata": {
		"version": 4.5,
		"type": "Object",
		"generator": "Object3D.toJSON"
	},
	"geometries": [
		{
			"uuid": "E2C8A9EF-5F10-43E2-8D81-3DAB96D33082",
			"type": "BufferGeometry",
			"data": {
				"attributes": {
					"position": {
						"itemSize": 3,
						"type": "Float32Array",
						"array": [-0.5,0,0.5,0.5,0,0.5,0.5,0,-0.5,-0.5,0,0.5,0.5,0,-0.5,-0.5,0,-0.5],
						"normalized": false
					},
					"normal": {
						"itemSize": 3,
						"type": "Float32Array",
						"array": [0,1,0,0,1,0,0,1,0,0,1,0,0,1,0,0,1,0],
						"normalized": false
					},
					"uv": {
						"itemSize": 2,
						"type": "Float32Array",
						"array": [1,0,1,1,0,1,1,0,0,1,0,0],
						"normalized": false
					}
				},
				"boundingSphere": {
					"center": [0,0,0],
					"radius": 0.707107
				}
			}
		},
		{
			"uuid": "653AAD1B-B716-40C5-98B0-5ED2DDA58DF8",
			"type": "BufferGeometry",
			"data": {
				"attributes": {
					"position": {
						"itemSize": 3,
						"type": "Float32Array",
						"array": [-0.5,0,0.5,0.5,0,0.5,0.5,0,-0.5,-0.5,0,0.5,0.5,0,-0.5,-0.5,0,-0.5],
						"normalized": false
					},
					"normal": {
						"itemSize": 3,
						"type": "Float32Array",
						"array": [0,1,0,0,1,0,0,1,0,0,1,0,0,1,0,0,1,0],
						"normalized": false
					},
					"uv": {
						"itemSize": 2,
						"type": "Float32Array",
						"array": [1,0,1,1,0,1,1,0,0,1,0,0],
						"normalized": false
					}
				},
				"boundingSphere": {
					"center": [0,0,0],
					"radius": 0.707107
				}
			}
		},
		{
			"uuid": "14EB61A0-ACD9-4F8E-A1F5-0ABEB339AAEA",
			"type": "BufferGeometry",
			"data": {
				"attributes": {
					"position": {
						"itemSize": 3,
						"type": "Float32Array",
						"array": [-0.5,0,0.5,0.5,0,0.5,0.5,0,-0.5,-0.5,0,0.5,0.5,0,-0.5,-0.5,0,-0.5],
						"normalized": false
					},
					"normal": {
						"itemSize": 3,
						"type": "Float32Array",
						"array": [0,1,0,0,1,0,0,1,0,0,1,0,0,1,0,0,1,0],
						"normalized": false
					},
					"uv": {
						"itemSize": 2,
						"type": "Float32Array",
						"array": [1,0,1,1,0,1,1,0,0,1,0,0],
						"normalized": false
					}
				},
				"boundingSphere": {
					"center": [0,0,0],
					"radius": 0.707107
				}
			}
		},
		{
			"uuid": "8243C295-0B4C-4379-99CC-BCA1DDBDCB37",
			"type": "BufferGeometry",
			"data": {
				"attributes": {
					"position": {
						"itemSize": 3,
						"type": "Float32Array",
						"array": [-0.5,0,0.5,0.5,0,0.5,0.5,0,-0.5,-0.5,0,0.5,0.5,0,-0.5,-0.5,0,-0.5],
						"normalized": false
					},
					"normal": {
						"itemSize": 3,
						"type": "Float32Array",
						"array": [0,1,0,0,1,0,0,1,0,0,1,0,0,1,0,0,1,0],
						"normalized": false
					},
					"uv": {
						"itemSize": 2,
						"type": "Float32Array",
						"array": [1,0,1,1,0,1,1,0,0,1,0,0],
						"normalized": false
					}
				},
				"boundingSphere": {
					"center": [0,0,0],
					"radius": 0.707107
				}
			}
		},
		{
			"uuid": "0335E017-5EB3-4D8F-9ACC-8CD5739CF063",
			"type": "BufferGeometry",
			"data": {
				"attributes": {
					"position": {
						"itemSize": 3,
						"type": "Float32Array",
						"array": [-0.5,0,0.5,0.5,0,0.5,0.5,0,-0.5,-0.5,0,0.5,0.5,0,-0.5,-0.5,0,-0.5],
						"normalized": false
					},
					"normal": {
						"itemSize": 3,
						"type": "Float32Array",
						"array": [0,1,0,0,1,0,0,1,0,0,1,0,0,1,0,0,1,0],
						"normalized": false
					},
					"uv": {
						"itemSize": 2,
						"type": "Float32Array",
						"array": [1,0,1,1,0,1,1,0,0,1,0,0],
						"normalized": false
					}
				},
				"boundingSphere": {
					"center": [0,0,0],
					"radius": 0.707107
				}
			}
		},
		{
			"uuid": "A6E31465-2BDA-4197-A11B-7447385ECDCC",
			"type": "BufferGeometry",
			"data": {
				"attributes": {
					"position": {
						"itemSize": 3,
						"type": "Float32Array",
						"array": [-0.5,0,0.5,0.5,0,0.5,0.5,0,-0.5,-0.5,0,0.5,0.5,0,-0.5,-0.5,0,-0.5],
						"normalized": false
					},
					"normal": {
						"itemSize": 3,
						"type": "Float32Array",
						"array": [0,1,0,0,1,0,0,1,0,0,1,0,0,1,0,0,1,0],
						"normalized": false
					},
					"uv": {
						"itemSize": 2,
						"type": "Float32Array",
						"array": [1,0,1,1,0,1,1,0,0,1,0,0],
						"normalized": false
					}
				},
				"boundingSphere": {
					"center": [0,0,0],
					"radius": 0.707107
				}
			}
		},
		{
			"uuid": "52CA7BA2-A521-4DBD-B402-9D05891FF57C",
			"type": "BufferGeometry",
			"data": {
				"attributes": {
					"position": {
						"itemSize": 3,
						"type": "Float32Array",
						"array": [-0.5,0,0.5,0.5,0,0.5,0.5,0,-0.5,-0.5,0,0.5,0.5,0,-0.5,-0.5,0,-0.5],
						"normalized": false
					},
					"normal": {
						"itemSize": 3,
						"type": "Float32Array",
						"array": [0,1,0,0,1,0,0,1,0,0,1,0,0,1,0,0,1,0],
						"normalized": false
					},
					"uv": {
						"itemSize": 2,
						"type": "Float32Array",
						"array": [1,0,1,1,0,1,1,0,0,1,0,0],
						"normalized": false
					}
				},
				"boundingSphere": {
					"center": [0,0,0],
					"radius": 0.707107
				}
			}
		},
		{
			"uuid": "6B8167CF-80B0-47F3-ACF4-400ACBDBBB1C",
			"type": "BufferGeometry",
			"data": {
				"attributes": {
					"position": {
						"itemSize": 3,
						"type": "Float32Array",
						"array": [-0.469114,-0.01616,0.515465,0.531901,0.01405,0.484535,0.469114,0.01616,-0.515465,-0.469114,-0.01616,0.515465,0.469114,0.01616,-0.515465,-0.531901,-0.01405,-0.484535],
						"normalized": false
					},
					"normal": {
						"itemSize": 3,
						"type": "Float32Array",
						"array": [-0.030043,0.999541,0.003996,-0.030043,0.999541,0.003996,-0.030043,0.999541,0.003996,-0.030043,0.999541,0.003996,-0.030043,0.999541,0.003996,-0.030043,0.999541,0.003996],
						"normalized": false
					},
					"uv": {
						"itemSize": 2,
						"type": "Float32Array",
						"array": [1,0,1,1,0,1,1,0,0,1,0,0],
						"normalized": false
					}
				},
				"boundingSphere": {
					"center": [0,0,0],
					"radius": 0.719646
				}
			}
		},
		{
			"uuid": "EE905561-9062-4835-AF6E-FC4323A06D67",
			"type": "BufferGeometry",
			"data": {
				"attributes": {
					"position": {
						"itemSize": 3,
						"type": "Float32Array",
						"array": [-0.543106,0.000213,0.487546,0.456894,-0.000213,0.512455,0.543106,-0.000213,-0.487545,-0.543106,0.000213,0.487546,0.543106,-0.000213,-0.487545,-0.456894,0.000213,-0.512455],
						"normalized": false
					},
					"normal": {
						"itemSize": 3,
						"type": "Float32Array",
						"array": [0.000424,1,0.000037,0.000424,1,0.000037,0.000424,1,0.000037,0.000424,1,0.000037,0.000424,1,0.000037,0.000424,1,0.000037],
						"normalized": false
					},
					"uv": {
						"itemSize": 2,
						"type": "Float32Array",
						"array": [1,0,1,1,0,1,1,0,0,1,0,0],
						"normalized": false
					}
				},
				"boundingSphere": {
					"center": [0,0,0],
					"radius": 0.729839
				}
			}
		},
		{
			"uuid": "8D9E4262-B0F2-465D-B353-CAE5119F9830",
			"type": "BufferGeometry",
			"data": {
				"attributes": {
					"position": {
						"itemSize": 3,
						"type": "Float32Array",
						"array": [-0.522844,-0.001095,0.488943,0.477156,-0.00152,0.513852,0.522844,0.001095,-0.488943,-0.522844,-0.001095,0.488943,0.522844,0.001095,-0.488943,-0.477156,0.00152,-0.513852],
						"normalized": false
					},
					"normal": {
						"itemSize": 3,
						"type": "Float32Array",
						"array": [0.00036,0.999996,0.002625,0.00036,0.999996,0.002625,0.00036,0.999996,0.002625,0.00036,0.999996,0.002625,0.00036,0.999996,0.002625,0.00036,0.999996,0.002625],
						"normalized": false
					},
					"uv": {
						"itemSize": 2,
						"type": "Float32Array",
						"array": [1,0,1,1,0,1,1,0,0,1,0,0],
						"normalized": false
					}
				},
				"boundingSphere": {
					"center": [0,0,0],
					"radius": 0.715844
				}
			}
		},
		{
			"uuid": "A4B73107-35EE-492D-8F10-B42D402A8C20",
			"type": "BufferGeometry",
			"data": {
				"attributes": {
					"position": {
						"itemSize": 3,
						"type": "Float32Array",
						"array": [-0.5,0,0.5,0.5,0,0.5,0.5,0,-0.5,-0.5,0,0.5,0.5,0,-0.5,-0.5,0,-0.5],
						"normalized": false
					},
					"normal": {
						"itemSize": 3,
						"type": "Float32Array",
						"array": [0,1,0,0,1,0,0,1,0,0,1,0,0,1,0,0,1,0],
						"normalized": false
					},
					"uv": {
						"itemSize": 2,
						"type": "Float32Array",
						"array": [1,0,1,1,0,1,1,0,0,1,0,0],
						"normalized": false
					}
				},
				"boundingSphere": {
					"center": [0,0,0],
					"radius": 0.707107
				}
			}
		},
		{
			"uuid": "E3071AFF-8CB9-4919-8CFF-BD608880393D",
			"type": "BufferGeometry",
			"data": {
				"attributes": {
					"position": {
						"itemSize": 3,
						"type": "Float32Array",
						"array": [-0.5,0,0.5,0.5,0,0.5,0.5,0,-0.5,-0.5,0,0.5,0.5,0,-0.5,-0.5,0,-0.5],
						"normalized": false
					},
					"normal": {
						"itemSize": 3,
						"type": "Float32Array",
						"array": [0,1,0,0,1,0,0,1,0,0,1,0,0,1,0,0,1,0],
						"normalized": false
					},
					"uv": {
						"itemSize": 2,
						"type": "Float32Array",
						"array": [1,0,1,1,0,1,1,0,0,1,0,0],
						"normalized": false
					}
				},
				"boundingSphere": {
					"center": [0,0,0],
					"radius": 0.707107
				}
			}
		},
		{
			"uuid": "B07B3B85-42DE-4D99-B224-B305C579117F",
			"type": "BufferGeometry",
			"data": {
				"attributes": {
					"position": {
						"itemSize": 3,
						"type": "Float32Array",
						"array": [-0.5,0,0.5,0.5,0,0.5,0.5,0,-0.5,-0.5,0,0.5,0.5,0,-0.5,-0.5,0,-0.5],
						"normalized": false
					},
					"normal": {
						"itemSize": 3,
						"type": "Float32Array",
						"array": [0,1,0,0,1,0,0,1,0,0,1,0,0,1,0,0,1,0],
						"normalized": false
					},
					"uv": {
						"itemSize": 2,
						"type": "Float32Array",
						"array": [1,0,1,1,0,1,1,0,0,1,0,0],
						"normalized": false
					}
				},
				"boundingSphere": {
					"center": [0,0,0],
					"radius": 0.707107
				}
			}
		},
		{
			"uuid": "3DE3B7E5-4401-4338-9048-1BD5D4A58D07",
			"type": "BufferGeometry",
			"data": {
				"attributes": {
					"position": {
						"itemSize": 3,
						"type": "Float32Array",
						"array": [-0.5,0,0.5,0.5,0,0.5,0.5,0,-0.5,-0.5,0,0.5,0.5,0,-0.5,-0.5,0,-0.5],
						"normalized": false
					},
					"normal": {
						"itemSize": 3,
						"type": "Float32Array",
						"array": [0,1,0,0,1,0,0,1,0,0,1,0,0,1,0,0,1,0],
						"normalized": false
					},
					"uv": {
						"itemSize": 2,
						"type": "Float32Array",
						"array": [1,0,1,1,0,1,1,0,0,1,0,0],
						"normalized": false
					}
				},
				"boundingSphere": {
					"center": [0,0,0],
					"radius": 0.707107
				}
			}
		},
		{
			"uuid": "064DC351-D301-40BC-B3FC-87B7076A3808",
			"type": "BufferGeometry",
			"data": {
				"attributes": {
					"position": {
						"itemSize": 3,
						"type": "Float32Array",
						"array": [-0.5,0,0.5,0.5,0,0.5,0.5,0,-0.5,-0.5,0,0.5,0.5,0,-0.5,-0.5,0,-0.5],
						"normalized": false
					},
					"normal": {
						"itemSize": 3,
						"type": "Float32Array",
						"array": [0,1,0,0,1,0,0,1,0,0,1,0,0,1,0,0,1,0],
						"normalized": false
					},
					"uv": {
						"itemSize": 2,
						"type": "Float32Array",
						"array": [1,0,1,1,0,1,1,0,0,1,0,0],
						"normalized": false
					}
				},
				"boundingSphere": {
					"center": [0,0,0],
					"radius": 0.707107
				}
			}
		},
		{
			"uuid": "878BBC7B-B28D-4AAA-8F98-93B90EEEAE14",
			"type": "BufferGeometry",
			"data": {
				"attributes": {
					"position": {
						"itemSize": 3,
						"type": "Float32Array",
						"array": [-0.5,0,0.5,0.5,0,0.5,0.5,0,-0.5,-0.5,0,0.5,0.5,0,-0.5,-0.5,0,-0.5],
						"normalized": false
					},
					"normal": {
						"itemSize": 3,
						"type": "Float32Array",
						"array": [0,1,0,0,1,0,0,1,0,0,1,0,0,1,0,0,1,0],
						"normalized": false
					},
					"uv": {
						"itemSize": 2,
						"type": "Float32Array",
						"array": [1,0,1,1,0,1,1,0,0,1,0,0],
						"normalized": false
					}
				},
				"boundingSphere": {
					"center": [0,0,0],
					"radius": 0.707107
				}
			}
		},
		{
			"uuid": "76286D96-ABD7-4057-A18C-129062CDF376",
			"type": "BufferGeometry",
			"data": {
				"attributes": {
					"position": {
						"itemSize": 3,
						"type": "Float32Array",
						"array": [-0.5,0,0.5,0.5,0,0.5,0.5,0,-0.5,-0.5,0,0.5,0.5,0,-0.5,-0.5,0,-0.5],
						"normalized": false
					},
					"normal": {
						"itemSize": 3,
						"type": "Float32Array",
						"array": [0,1,0,0,1,0,0,1,0,0,1,0,0,1,0,0,1,0],
						"normalized": false
					},
					"uv": {
						"itemSize": 2,
						"type": "Float32Array",
						"array": [1,0,1,1,0,1,1,0,0,1,0,0],
						"normalized": false
					}
				},
				"boundingSphere": {
					"center": [0,0,0],
					"radius": 0.707107
				}
			}
		},
		{
			"uuid": "1D4616E8-30C0-4586-AB7C-F93BF0DA76C5",
			"type": "BufferGeometry",
			"data": {
				"attributes": {
					"position": {
						"itemSize": 3,
						"type": "Float32Array",
						"array": [-0.5,0,0.5,0.5,0,0.5,0.5,0,-0.5,-0.5,0,0.5,0.5,0,-0.5,-0.5,0,-0.5],
						"normalized": false
					},
					"normal": {
						"itemSize": 3,
						"type": "Float32Array",
						"array": [0,1,0,0,1,0,0,1,0,0,1,0,0,1,0,0,1,0],
						"normalized": false
					},
					"uv": {
						"itemSize": 2,
						"type": "Float32Array",
						"array": [1,0,1,1,0,1,1,0,0,1,0,0],
						"normalized": false
					}
				},
				"boundingSphere": {
					"center": [0,0,0],
					"radius": 0.707107
				}
			}
		},
		{
			"uuid": "59BC89D3-957F-44DC-88B3-20AB07DD08F3",
			"type": "BufferGeometry",
			"data": {
				"attributes": {
					"position": {
						"itemSize": 3,
						"type": "Float32Array",
						"array": [-0.5,0,0.5,0.5,0,0.5,0.5,0,-0.5,-0.5,0,0.5,0.5,0,-0.5,-0.5,0,-0.5],
						"normalized": false
					},
					"normal": {
						"itemSize": 3,
						"type": "Float32Array",
						"array": [0,1,0,0,1,0,0,1,0,0,1,0,0,1,0,0,1,0],
						"normalized": false
					},
					"uv": {
						"itemSize": 2,
						"type": "Float32Array",
						"array": [1,0,1,1,0,1,1,0,0,1,0,0],
						"normalized": false
					}
				},
				"boundingSphere": {
					"center": [0,0,0],
					"radius": 0.707107
				}
			}
		},
		{
			"uuid": "AB1EE80D-94BD-4534-9F30-F376258B6DD1",
			"type": "BufferGeometry",
			"data": {
				"attributes": {
					"position": {
						"itemSize": 3,
						"type": "Float32Array",
						"array": [-0.5,0,0.5,0.5,0,0.5,0.5,0,-0.5,-0.5,0,0.5,0.5,0,-0.5,-0.5,0,-0.5],
						"normalized": false
					},
					"normal": {
						"itemSize": 3,
						"type": "Float32Array",
						"array": [0,1,0,0,1,0,0,1,0,0,1,0,0,1,0,0,1,0],
						"normalized": false
					},
					"uv": {
						"itemSize": 2,
						"type": "Float32Array",
						"array": [1,0,1,1,0,1,1,0,0,1,0,0],
						"normalized": false
					}
				},
				"boundingSphere": {
					"center": [0,0,0],
					"radius": 0.707107
				}
			}
		},
		{
			"uuid": "BEA11C78-1C8B-4C27-90E2-8157A8EADF24",
			"type": "BufferGeometry",
			"data": {
				"attributes": {
					"position": {
						"itemSize": 3,
						"type": "Float32Array",
						"array": [-0.5,0,0.5,0.5,0,0.5,0.5,0,-0.5,-0.5,0,0.5,0.5,0,-0.5,-0.5,0,-0.5],
						"normalized": false
					},
					"normal": {
						"itemSize": 3,
						"type": "Float32Array",
						"array": [0,1,0,0,1,0,0,1,0,0,1,0,0,1,0,0,1,0],
						"normalized": false
					},
					"uv": {
						"itemSize": 2,
						"type": "Float32Array",
						"array": [1,0,1,1,0,1,1,0,0,1,0,0],
						"normalized": false
					}
				},
				"boundingSphere": {
					"center": [0,0,0],
					"radius": 0.707107
				}
			}
		},
		{
			"uuid": "6557BDC1-B29C-488F-8FB7-574998B6FE8A",
			"type": "BufferGeometry",
			"data": {
				"attributes": {
					"position": {
						"itemSize": 3,
						"type": "Float32Array",
						"array": [-0.5,0,0.5,0.5,0,0.5,0.5,0,-0.5,-0.5,0,0.5,0.5,0,-0.5,-0.5,0,-0.5],
						"normalized": false
					},
					"normal": {
						"itemSize": 3,
						"type": "Float32Array",
						"array": [0,1,0,0,1,0,0,1,0,0,1,0,0,1,0,0,1,0],
						"normalized": false
					},
					"uv": {
						"itemSize": 2,
						"type": "Float32Array",
						"array": [1,0,1,1,0,1,1,0,0,1,0,0],
						"normalized": false
					}
				},
				"boundingSphere": {
					"center": [0,0,0],
					"radius": 0.707107
				}
			}
		},
		{
			"uuid": "52CE19EA-A2C1-47B1-9D7B-B3B4A6B7C2D6",
			"type": "BufferGeometry",
			"data": {
				"attributes": {
					"position": {
						"itemSize": 3,
						"type": "Float32Array",
						"array": [-0.5,0,0.5,0.5,0,0.5,0.5,0,-0.5,-0.5,0,0.5,0.5,0,-0.5,-0.5,0,-0.5],
						"normalized": false
					},
					"normal": {
						"itemSize": 3,
						"type": "Float32Array",
						"array": [0,1,0,0,1,0,0,1,0,0,1,0,0,1,0,0,1,0],
						"normalized": false
					},
					"uv": {
						"itemSize": 2,
						"type": "Float32Array",
						"array": [1,0,1,1,0,1,1,0,0,1,0,0],
						"normalized": false
					}
				},
				"boundingSphere": {
					"center": [0,0,0],
					"radius": 0.707107
				}
			}
		},
		{
			"uuid": "1EA0326D-DE1A-41D4-B7DB-76659B565EFF",
			"type": "BufferGeometry",
			"data": {
				"attributes": {
					"position": {
						"itemSize": 3,
						"type": "Float32Array",
						"array": [-0.5,0,0.5,0.5,0,0.5,0.5,0,-0.5,-0.5,0,0.5,0.5,0,-0.5,-0.5,0,-0.5],
						"normalized": false
					},
					"normal": {
						"itemSize": 3,
						"type": "Float32Array",
						"array": [0,1,0,0,1,0,0,1,0,0,1,0,0,1,0,0,1,0],
						"normalized": false
					},
					"uv": {
						"itemSize": 2,
						"type": "Float32Array",
						"array": [1,0,1,1,0,1,1,0,0,1,0,0],
						"normalized": false
					}
				},
				"boundingSphere": {
					"center": [0,0,0],
					"radius": 0.707107
				}
			}
		},
		{
			"uuid": "8ABB8F5F-CC64-46C6-AA47-056C3D4AE4B5",
			"type": "BufferGeometry",
			"data": {
				"attributes": {
					"position": {
						"itemSize": 3,
						"type": "Float32Array",
						"array": [-0.5,0,0.5,0.5,0,0.5,0.5,0,-0.5,-0.5,0,0.5,0.5,0,-0.5,-0.5,0,-0.5],
						"normalized": false
					},
					"normal": {
						"itemSize": 3,
						"type": "Float32Array",
						"array": [0,1,0,0,1,0,0,1,0,0,1,0,0,1,0,0,1,0],
						"normalized": false
					},
					"uv": {
						"itemSize": 2,
						"type": "Float32Array",
						"array": [1,0,1,1,0,1,1,0,0,1,0,0],
						"normalized": false
					}
				},
				"boundingSphere": {
					"center": [0,0,0],
					"radius": 0.707107
				}
			}
		},
		{
			"uuid": "520253F0-59B7-4FE8-A5E0-082A2275D153",
			"type": "BufferGeometry",
			"data": {
				"attributes": {
					"position": {
						"itemSize": 3,
						"type": "Float32Array",
						"array": [-0.517815,-0.005219,0.499547,0.482212,0.005314,0.499603,0.517815,0.005219,-0.499547,-0.517815,-0.005219,0.499547,0.517815,0.005219,-0.499547,-0.482212,-0.005314,-0.499603],
						"normalized": false
					},
					"normal": {
						"itemSize": 3,
						"type": "Float32Array",
						"array": [-0.010532,0.999944,-0.00047,-0.010532,0.999944,-0.00047,-0.010532,0.999944,-0.00047,-0.010532,0.999944,-0.00047,-0.010532,0.999944,-0.00047,-0.010532,0.999944,-0.00047],
						"normalized": false
					},
					"uv": {
						"itemSize": 2,
						"type": "Float32Array",
						"array": [1,0,1,1,0,1,1,0,0,1,0,0],
						"normalized": false
					}
				},
				"boundingSphere": {
					"center": [0,0,0],
					"radius": 0.719518
				}
			}
		},
		{
			"uuid": "BEF29026-6676-4546-8AA4-A405A06D9A93",
			"type": "BufferGeometry",
			"data": {
				"attributes": {
					"position": {
						"itemSize": 3,
						"type": "Float32Array",
						"array": [-0.513588,0.000036,0.499676,0.486412,0.000036,0.499676,0.513588,-0.000036,-0.499676,-0.513588,0.000036,0.499676,0.513588,-0.000036,-0.499676,-0.486412,-0.000036,-0.499676],
						"normalized": false
					},
					"normal": {
						"itemSize": 3,
						"type": "Float32Array",
						"array": [0,1,-0.000072,0,1,-0.000072,0,1,-0.000072,0,1,-0.000072,0,1,-0.000072,0,1,-0.000072],
						"normalized": false
					},
					"uv": {
						"itemSize": 2,
						"type": "Float32Array",
						"array": [1,0,1,1,0,1,1,0,0,1,0,0],
						"normalized": false
					}
				},
				"boundingSphere": {
					"center": [0,0,0],
					"radius": 0.716553
				}
			}
		},
		{
			"uuid": "1D55D218-C339-4569-ABE6-7C24DB290FA3",
			"type": "BufferGeometry",
			"data": {
				"attributes": {
					"position": {
						"itemSize": 3,
						"type": "Float32Array",
						"array": [-0.335316,-0.00218,0.499606,0.500801,0.001733,0.500022,0.517922,0.001324,-0.500022,-0.335316,-0.00218,0.499606,0.517922,0.001324,-0.500022,-0.517922,0.00218,-0.499931],
						"normalized": false
					},
					"normal": {
						"itemSize": 3,
						"type": "Float32Array",
						"array": [-0.001634,0.999996,0.002111,-0.001634,0.999996,0.002111,-0.001634,0.999996,0.002111,-0.001634,0.999996,0.002111,-0.001634,0.999996,0.002111,-0.001634,0.999996,0.002111],
						"normalized": false
					},
					"uv": {
						"itemSize": 2,
						"type": "Float32Array",
						"array": [1,0,1,1,0,1,1,0,0,1,0,0],
						"normalized": false
					}
				},
				"boundingSphere": {
					"center": [0,0,0],
					"radius": 0.719907
				}
			}
		},
		{
			"uuid": "F632F3FC-1146-4B57-A804-7CDF5A6E08A5",
			"type": "BufferGeometry",
			"data": {
				"attributes": {
					"position": {
						"itemSize": 3,
						"type": "Float32Array",
						"array": [-0.5,0,0.5,0.5,0,0.5,0.5,0,-0.5,-0.5,0,0.5,0.5,0,-0.5,-0.5,0,-0.5],
						"normalized": false
					},
					"normal": {
						"itemSize": 3,
						"type": "Float32Array",
						"array": [0,1,0,0,1,0,0,1,0,0,1,0,0,1,0,0,1,0],
						"normalized": false
					},
					"uv": {
						"itemSize": 2,
						"type": "Float32Array",
						"array": [0,1,0,0,1,0,0,1,1,0,1,1],
						"normalized": false
					}
				},
				"boundingSphere": {
					"center": [0,0,0],
					"radius": 0.707107
				}
			}
		},
		{
			"uuid": "03FF56F8-D813-46B1-ACCA-4E1F253EFDBD",
			"type": "BufferGeometry",
			"data": {
				"attributes": {
					"position": {
						"itemSize": 3,
						"type": "Float32Array",
						"array": [-0.5,0,0.5,0.5,0,0.5,0.5,0,-0.5,-0.5,0,0.5,0.5,0,-0.5,-0.5,0,-0.5],
						"normalized": false
					},
					"normal": {
						"itemSize": 3,
						"type": "Float32Array",
						"array": [0,1,0,0,1,0,0,1,0,0,1,0,0,1,0,0,1,0],
						"normalized": false
					},
					"uv": {
						"itemSize": 2,
						"type": "Float32Array",
						"array": [0,1,0,0,1,0,0,1,1,0,1,1],
						"normalized": false
					}
				},
				"boundingSphere": {
					"center": [0,0,0],
					"radius": 0.707107
				}
			}
		},
		{
			"uuid": "C14FBD43-04C8-45FC-BE52-B6E01AF22A11",
			"type": "BufferGeometry",
			"data": {
				"attributes": {
					"position": {
						"itemSize": 3,
						"type": "Float32Array",
						"array": [-0.5,0,0.5,0.5,0,0.5,0.5,0,-0.5,-0.5,0,0.5,0.5,0,-0.5,-0.5,0,-0.5],
						"normalized": false
					},
					"normal": {
						"itemSize": 3,
						"type": "Float32Array",
						"array": [0,1,0,0,1,0,0,1,0,0,1,0,0,1,0,0,1,0],
						"normalized": false
					},
					"uv": {
						"itemSize": 2,
						"type": "Float32Array",
						"array": [0,1,0,0,1,0,0,1,1,0,1,1],
						"normalized": false
					}
				},
				"boundingSphere": {
					"center": [0,0,0],
					"radius": 0.707107
				}
			}
		},
		{
			"uuid": "B4F1E32B-815F-41FB-AD07-B34673E3BD04",
			"type": "BufferGeometry",
			"data": {
				"attributes": {
					"position": {
						"itemSize": 3,
						"type": "Float32Array",
						"array": [-0.5,0,0.5,0.5,0,0.5,0.5,0,-0.5,-0.5,0,0.5,0.5,0,-0.5,-0.5,0,-0.5],
						"normalized": false
					},
					"normal": {
						"itemSize": 3,
						"type": "Float32Array",
						"array": [0,1,0,0,1,0,0,1,0,0,1,0,0,1,0,0,1,0],
						"normalized": false
					},
					"uv": {
						"itemSize": 2,
						"type": "Float32Array",
						"array": [0,1,0,0,1,0,0,1,1,0,1,1],
						"normalized": false
					}
				},
				"boundingSphere": {
					"center": [0,0,0],
					"radius": 0.707107
				}
			}
		},
		{
			"uuid": "4ACB72E7-2C92-4CF5-BC9C-434CEF6D4A41",
			"type": "BufferGeometry",
			"data": {
				"attributes": {
					"position": {
						"itemSize": 3,
						"type": "Float32Array",
						"array": [-0.5,0,0.5,0.5,0,0.5,0.5,0,-0.5,-0.5,0,0.5,0.5,0,-0.5,-0.5,0,-0.5],
						"normalized": false
					},
					"normal": {
						"itemSize": 3,
						"type": "Float32Array",
						"array": [0,1,0,0,1,0,0,1,0,0,1,0,0,1,0,0,1,0],
						"normalized": false
					},
					"uv": {
						"itemSize": 2,
						"type": "Float32Array",
						"array": [0,1,0,0,1,0,0,1,1,0,1,1],
						"normalized": false
					}
				},
				"boundingSphere": {
					"center": [0,0,0],
					"radius": 0.707107
				}
			}
		},
		{
			"uuid": "5C7F77A3-869D-4521-A2D0-4093DF273142",
			"type": "BufferGeometry",
			"data": {
				"attributes": {
					"position": {
						"itemSize": 3,
						"type": "Float32Array",
						"array": [-0.5,0,0.5,0.5,0,0.5,0.5,0,-0.5,-0.5,0,0.5,0.5,0,-0.5,-0.5,0,-0.5],
						"normalized": false
					},
					"normal": {
						"itemSize": 3,
						"type": "Float32Array",
						"array": [0,1,0,0,1,0,0,1,0,0,1,0,0,1,0,0,1,0],
						"normalized": false
					},
					"uv": {
						"itemSize": 2,
						"type": "Float32Array",
						"array": [0,1,0,0,1,0,0,1,1,0,1,1],
						"normalized": false
					}
				},
				"boundingSphere": {
					"center": [0,0,0],
					"radius": 0.707107
				}
			}
		},
		{
			"uuid": "AEE13806-3827-4ED8-95E6-1AD4BF8BA6EC",
			"type": "BufferGeometry",
			"data": {
				"attributes": {
					"position": {
						"itemSize": 3,
						"type": "Float32Array",
						"array": [-0.5,0,0.5,0.5,0,0.5,0.5,0,-0.5,-0.5,0,0.5,0.5,0,-0.5,-0.5,0,-0.5],
						"normalized": false
					},
					"normal": {
						"itemSize": 3,
						"type": "Float32Array",
						"array": [0,1,0,0,1,0,0,1,0,0,1,0,0,1,0,0,1,0],
						"normalized": false
					},
					"uv": {
						"itemSize": 2,
						"type": "Float32Array",
						"array": [0,1,0,0,1,0,0,1,1,0,1,1],
						"normalized": false
					}
				},
				"boundingSphere": {
					"center": [0,0,0],
					"radius": 0.707107
				}
			}
		},
		{
			"uuid": "BE0F31E7-B9F1-43D6-9C6A-157F1124B0A0",
			"type": "BufferGeometry",
			"data": {
				"attributes": {
					"position": {
						"itemSize": 3,
						"type": "Float32Array",
						"array": [-0.5,0,0.5,0.5,0,0.5,0.5,0,-0.5,-0.5,0,0.5,0.5,0,-0.5,-0.5,0,-0.5],
						"normalized": false
					},
					"normal": {
						"itemSize": 3,
						"type": "Float32Array",
						"array": [0,1,0,0,1,0,0,1,0,0,1,0,0,1,0,0,1,0],
						"normalized": false
					},
					"uv": {
						"itemSize": 2,
						"type": "Float32Array",
						"array": [0,1,0,0,1,0,0,1,1,0,1,1],
						"normalized": false
					}
				},
				"boundingSphere": {
					"center": [0,0,0],
					"radius": 0.707107
				}
			}
		},
		{
			"uuid": "0C5F3259-BBEB-4124-A5E4-D30F960174E0",
			"type": "BufferGeometry",
			"data": {
				"attributes": {
					"position": {
						"itemSize": 3,
						"type": "Float32Array",
						"array": [-0.5,0,0.5,0.5,0,0.5,0.5,0,-0.5,-0.5,0,0.5,0.5,0,-0.5,-0.5,0,-0.5],
						"normalized": false
					},
					"normal": {
						"itemSize": 3,
						"type": "Float32Array",
						"array": [0,1,0,0,1,0,0,1,0,0,1,0,0,1,0,0,1,0],
						"normalized": false
					},
					"uv": {
						"itemSize": 2,
						"type": "Float32Array",
						"array": [1,0,1,1,0,1,1,0,0,1,0,0],
						"normalized": false
					}
				},
				"boundingSphere": {
					"center": [0,0,0],
					"radius": 0.707107
				}
			}
		},
		{
			"uuid": "1CC10461-5B56-4B69-AAD5-A67EE97F27E2",
			"type": "BufferGeometry",
			"data": {
				"attributes": {
					"position": {
						"itemSize": 3,
						"type": "Float32Array",
						"array": [-0.5,0,0.5,0.5,0,0.5,0.5,0,-0.5,-0.5,0,0.5,0.5,0,-0.5,-0.5,0,-0.5],
						"normalized": false
					},
					"normal": {
						"itemSize": 3,
						"type": "Float32Array",
						"array": [0,1,0,0,1,0,0,1,0,0,1,0,0,1,0,0,1,0],
						"normalized": false
					},
					"uv": {
						"itemSize": 2,
						"type": "Float32Array",
						"array": [1,0,1,1,0,1,1,0,0,1,0,0],
						"normalized": false
					}
				},
				"boundingSphere": {
					"center": [0,0,0],
					"radius": 0.707107
				}
			}
		},
		{
			"uuid": "E2F043ED-F275-41F6-B0FE-B5637A173E28",
			"type": "BufferGeometry",
			"data": {
				"attributes": {
					"position": {
						"itemSize": 3,
						"type": "Float32Array",
						"array": [-0.5,0,0.5,0.5,0,0.5,0.5,0,-0.5,-0.5,0,0.5,0.5,0,-0.5,-0.5,0,-0.5],
						"normalized": false
					},
					"normal": {
						"itemSize": 3,
						"type": "Float32Array",
						"array": [0,1,0,0,1,0,0,1,0,0,1,0,0,1,0,0,1,0],
						"normalized": false
					},
					"uv": {
						"itemSize": 2,
						"type": "Float32Array",
						"array": [1,0,1,1,0,1,1,0,0,1,0,0],
						"normalized": false
					}
				},
				"boundingSphere": {
					"center": [0,0,0],
					"radius": 0.707107
				}
			}
		},
		{
			"uuid": "283F13DF-126D-4A7E-9DE6-78EE1668A19B",
			"type": "BufferGeometry",
			"data": {
				"attributes": {
					"position": {
						"itemSize": 3,
						"type": "Float32Array",
						"array": [-0.5,0,0.5,0.5,0,0.5,0.5,0,-0.5,-0.5,0,0.5,0.5,0,-0.5,-0.5,0,-0.5],
						"normalized": false
					},
					"normal": {
						"itemSize": 3,
						"type": "Float32Array",
						"array": [0,1,0,0,1,0,0,1,0,0,1,0,0,1,0,0,1,0],
						"normalized": false
					},
					"uv": {
						"itemSize": 2,
						"type": "Float32Array",
						"array": [1,0,1,1,0,1,1,0,0,1,0,0],
						"normalized": false
					}
				},
				"boundingSphere": {
					"center": [0,0,0],
					"radius": 0.707107
				}
			}
		},
		{
			"uuid": "3B461168-4D5D-4E54-8FB9-40FB3A9073B2",
			"type": "BufferGeometry",
			"data": {
				"attributes": {
					"position": {
						"itemSize": 3,
						"type": "Float32Array",
						"array": [-0.5,0,0.5,0.5,0,0.5,0.5,0,-0.5,-0.5,0,0.5,0.5,0,-0.5,-0.5,0,-0.5],
						"normalized": false
					},
					"normal": {
						"itemSize": 3,
						"type": "Float32Array",
						"array": [0,1,0,0,1,0,0,1,0,0,1,0,0,1,0,0,1,0],
						"normalized": false
					},
					"uv": {
						"itemSize": 2,
						"type": "Float32Array",
						"array": [1,0,1,1,0,1,1,0,0,1,0,0],
						"normalized": false
					}
				},
				"boundingSphere": {
					"center": [0,0,0],
					"radius": 0.707107
				}
			}
		}],
	"materials": [
		{
			"uuid": "F8D6A31D-3EB2-41D7-92DC-8AA39212903D",
			"type": "MeshPhongMaterial",
			"name": "blinn20",
			"color": 6710886,
			"emissive": 0,
			"specular": 8355711,
			"shininess": 6.311791,
			"depthFunc": 3,
			"depthTest": true,
			"depthWrite": true,
			"stencilWrite": false,
			"stencilWriteMask": 255,
			"stencilFunc": 519,
			"stencilRef": 0,
			"stencilFuncMask": 255,
			"stencilFail": 7680,
			"stencilZFail": 7680,
			"stencilZPass": 7680
		}],
	"object": {
		"uuid": "8303E955-D346-4411-9B45-4AA9100B5130",
		"type": "Group",
		"name": "ModelRoot",
		"userData": {
			"transformData": {
				"inheritType": 1,
				"eulerOrder": "ZYX",
				"parentMatrixWorld": {
					"elements": [1,0,0,0,0,1,0,0,0,0,1,0,0,0,0,1]
				}
			}
		},
		"layers": 1,
		"matrix": [1,0,0,0,0,1,0,0,0,0,1,0,0,0,0,1],
		"children": [
			{
				"uuid": "7AC77A24-3C12-4C0A-9C04-70602E1AA37D",
				"type": "Mesh",
				"name": "P1_1_1",
				"userData": {
					"transformData": {
						"inheritType": 1,
						"eulerOrder": "ZYX",
						"translation": [49.9,13.822059,43.793305],
						"rotation": [0,0,90],
						"scale": [5,5,5],
						"parentMatrixWorld": {
							"elements": [1,0,0,0,0,1,0,0,0,0,1,0,0,0,0,1]
						}
					}
				},
				"layers": 1,
				"matrix": [0,5,0,0,-5,0,0,0,0,0,5,0,49.9,13.822059,43.793305,1],
				"geometry": "E2C8A9EF-5F10-43E2-8D81-3DAB96D33082",
				"material": "F8D6A31D-3EB2-41D7-92DC-8AA39212903D"
			},
			{
				"uuid": "1D1DFB92-B209-4E36-8CC9-E10247FB9590",
				"type": "Mesh",
				"name": "P2_1_1",
				"userData": {
					"transformData": {
						"inheritType": 1,
						"eulerOrder": "ZYX",
						"translation": [49.9,13.822059,49.316052],
						"rotation": [0,0,90],
						"scale": [5,5,5],
						"parentMatrixWorld": {
							"elements": [1,0,0,0,0,1,0,0,0,0,1,0,0,0,0,1]
						}
					}
				},
				"layers": 1,
				"matrix": [0,5,0,0,-5,0,0,0,0,0,5,0,49.9,13.822059,49.316052,1],
				"geometry": "653AAD1B-B716-40C5-98B0-5ED2DDA58DF8",
				"material": "F8D6A31D-3EB2-41D7-92DC-8AA39212903D"
			},
			{
				"uuid": "93EC24D8-DE34-4827-B394-AFA5B0337D5A",
				"type": "Mesh",
				"name": "P3_1_1",
				"userData": {
					"transformData": {
						"inheritType": 1,
						"eulerOrder": "ZYX",
						"translation": [49.9,8.399724,43.793305],
						"rotation": [0,0,90],
						"scale": [4.2,4.2,4.2],
						"parentMatrixWorld": {
							"elements": [1,0,0,0,0,1,0,0,0,0,1,0,0,0,0,1]
						}
					}
				},
				"layers": 1,
				"matrix": [0,4.2,0,0,-4.2,0,0,0,0,0,4.2,0,49.9,8.399724,43.793305,1],
				"geometry": "14EB61A0-ACD9-4F8E-A1F5-0ABEB339AAEA",
				"material": "F8D6A31D-3EB2-41D7-92DC-8AA39212903D"
			},
			{
				"uuid": "9CA1F831-C520-4009-AE24-D76FEEA1CE91",
				"type": "Mesh",
				"name": "P4_1_1",
				"userData": {
					"transformData": {
						"inheritType": 1,
						"eulerOrder": "ZYX",
						"translation": [49.9,8.399724,48.445274],
						"rotation": [0,0,90],
						"scale": [4.2,4.2,4.2],
						"parentMatrixWorld": {
							"elements": [1,0,0,0,0,1,0,0,0,0,1,0,0,0,0,1]
						}
					}
				},
				"layers": 1,
				"matrix": [0,4.2,0,0,-4.2,0,0,0,0,0,4.2,0,49.9,8.399724,48.445274,1],
				"geometry": "8243C295-0B4C-4379-99CC-BCA1DDBDCB37",
				"material": "F8D6A31D-3EB2-41D7-92DC-8AA39212903D"
			},
			{
				"uuid": "105B8076-D1E4-488E-8130-DE997A3AD52A",
				"type": "Mesh",
				"name": "P5_1_1",
				"userData": {
					"transformData": {
						"inheritType": 1,
						"eulerOrder": "ZYX",
						"translation": [49.9,3.712579,48.132318],
						"rotation": [0,0,90],
						"scale": [4,4,4],
						"parentMatrixWorld": {
							"elements": [1,0,0,0,0,1,0,0,0,0,1,0,0,0,0,1]
						}
					}
				},
				"layers": 1,
				"matrix": [0,4,0,0,-4,0,0,0,0,0,4,0,49.9,3.712579,48.132318,1],
				"geometry": "0335E017-5EB3-4D8F-9ACC-8CD5739CF063",
				"material": "F8D6A31D-3EB2-41D7-92DC-8AA39212903D"
			},
			{
				"uuid": "54EF1819-3FBB-4593-8B32-A3AC6209488E",
				"type": "Mesh",
				"name": "P6_1_1",
				"userData": {
					"transformData": {
						"inheritType": 1,
						"eulerOrder": "ZYX",
						"translation": [45.041782,-4.384359,48.911937],
						"rotation": [-57.143638,0,90],
						"scale": [4,4,4],
						"parentMatrixWorld": {
							"elements": [1,0,0,0,0,1,0,0,0,0,1,0,0,0,0,1]
						}
					}
				},
				"layers": 1,
				"matrix": [0,4,0,0,-2.170139,0,-3.360133,0,-3.360133,0,2.170139,0,45.041782,-4.384359,48.911937,1],
				"geometry": "A6E31465-2BDA-4197-A11B-7447385ECDCC",
				"material": "F8D6A31D-3EB2-41D7-92DC-8AA39212903D"
			},
			{
				"uuid": "980925EE-65D0-4053-920C-D094DDE7B728",
				"type": "Mesh",
				"name": "P7_1_1",
				"userData": {
					"transformData": {
						"inheritType": 1,
						"eulerOrder": "ZYX",
						"translation": [36.746882,-2.909056,48.987443],
						"rotation": [-61.687532,0,90],
						"scale": [4,4,4],
						"parentMatrixWorld": {
							"elements": [1,0,0,0,0,1,0,0,0,0,1,0,0,0,0,1]
						}
					}
				},
				"layers": 1,
				"matrix": [0,4,0,0,-1.897119,0,-3.521497,0,-3.521497,0,1.897119,0,36.746882,-2.909056,48.987443,1],
				"geometry": "52CA7BA2-A521-4DBD-B402-9D05891FF57C",
				"material": "F8D6A31D-3EB2-41D7-92DC-8AA39212903D"
			},
			{
				"uuid": "77F7CF07-03A6-492D-BADB-01D7E938608F",
				"type": "Mesh",
				"name": "P8_1_1",
				"userData": {
					"transformData": {
						"inheritType": 1,
						"eulerOrder": "ZYX",
						"translation": [46.597164,-10.297316,46.436966],
						"rotation": [-44.325847,1.345267,91.376912],
						"scale": [6,6,6],
						"parentMatrixWorld": {
							"elements": [1,0,0,0,0,1,0,0,0,0,1,0,0,0,0,1]
						}
					}
				},
				"layers": 1,
				"matrix": [-0.144136,5.996614,-0.140863,0,-4.288661,-0.201538,-4.191273,0,-4.193639,0,4.291083,0,46.597164,-10.297316,46.436966,1],
				"geometry": "6B8167CF-80B0-47F3-ACF4-400ACBDBBB1C",
				"material": "F8D6A31D-3EB2-41D7-92DC-8AA39212903D"
			},
			{
				"uuid": "42EF84F9-2B90-4A63-8FB3-283D123B5DD7",
				"type": "Mesh",
				"name": "P9_1_1",
				"userData": {
					"transformData": {
						"inheritType": 1,
						"eulerOrder": "ZYX",
						"translation": [47.075329,-17.501491,36.711705],
						"rotation": [-26.218493,2.27797,92.229224],
						"scale": [6,6,6],
						"parentMatrixWorld": {
							"elements": [1,0,0,0,0,1,0,0,0,0,1,0,0,0,0,1]
						}
					}
				},
				"layers": 1,
				"matrix": [-0.2332,5.990721,-0.238486,0,-5.374523,-0.314655,-2.648678,0,-2.657089,0.110679,5.378441,0,47.075329,-17.501491,36.711705,1],
				"geometry": "EE905561-9062-4835-AF6E-FC4323A06D67",
				"material": "F8D6A31D-3EB2-41D7-92DC-8AA39212903D"
			},
			{
				"uuid": "86F807A9-F695-4285-B457-D4F69597F5B8",
				"type": "Mesh",
				"name": "P10_1_1",
				"userData": {
					"transformData": {
						"inheritType": 1,
						"eulerOrder": "ZYX",
						"translation": [35.495783,-16.962472,46.624788],
						"rotation": [-33.238101,5.316046,90.923644],
						"scale": [6,6,6],
						"parentMatrixWorld": {
							"elements": [1,0,0,0,0,1,0,0,0,0,1,0,0,0,0,1]
						}
					}
				},
				"layers": 1,
				"matrix": [-0.096304,5.973416,-0.555897,0,-5.012836,-0.385554,-3.274572,0,-3.295785,0.411878,4.996815,0,35.495783,-16.962472,46.624788,1],
				"geometry": "8D9E4262-B0F2-465D-B353-CAE5119F9830",
				"material": "F8D6A31D-3EB2-41D7-92DC-8AA39212903D"
			},
			{
				"uuid": "4052666E-9889-40AD-AB3A-4D7597E69793",
				"type": "Mesh",
				"name": "P15_1_1",
				"userData": {
					"transformData": {
						"inheritType": 1,
						"eulerOrder": "ZYX",
						"translation": [-49.5,8.769937,23.9065],
						"rotation": [180,0,90],
						"scale": [7,7,7],
						"parentMatrixWorld": {
							"elements": [1,0,0,0,0,1,0,0,0,0,1,0,0,0,0,1]
						}
					}
				},
				"layers": 1,
				"matrix": [0,7,0,0,7,0,0,0,0,0,-7,0,-49.5,8.769937,23.9065,1],
				"geometry": "A4B73107-35EE-492D-8F10-B42D402A8C20",
				"material": "F8D6A31D-3EB2-41D7-92DC-8AA39212903D"
			},
			{
				"uuid": "4DD16D40-426E-44F2-BAE6-DEEFB86358C1",
				"type": "Mesh",
				"name": "P11_1_1",
				"userData": {
					"transformData": {
						"inheritType": 1,
						"eulerOrder": "ZYX",
						"translation": [-49.5,16.670658,17.048509],
						"rotation": [180,0,90],
						"scale": [7,7,7],
						"parentMatrixWorld": {
							"elements": [1,0,0,0,0,1,0,0,0,0,1,0,0,0,0,1]
						}
					}
				},
				"layers": 1,
				"matrix": [0,7,0,0,7,0,0,0,0,0,-7,0,-49.5,16.670658,17.048509,1],
				"geometry": "E3071AFF-8CB9-4919-8CFF-BD608880393D",
				"material": "F8D6A31D-3EB2-41D7-92DC-8AA39212903D"
			},
			{
				"uuid": "71277796-AFC5-478F-A55D-6ECA180E0049",
				"type": "Mesh",
				"name": "P12_1_1",
				"userData": {
					"transformData": {
						"inheritType": 1,
						"eulerOrder": "ZYX",
						"translation": [-49.5,17.066175,8.962346],
						"rotation": [180,0,90],
						"scale": [7,7,7],
						"parentMatrixWorld": {
							"elements": [1,0,0,0,0,1,0,0,0,0,1,0,0,0,0,1]
						}
					}
				},
				"layers": 1,
				"matrix": [0,7,0,0,7,0,0,0,0,0,-7,0,-49.5,17.066175,8.962346,1],
				"geometry": "B07B3B85-42DE-4D99-B224-B305C579117F",
				"material": "F8D6A31D-3EB2-41D7-92DC-8AA39212903D"
			},
			{
				"uuid": "4492A0A1-EF07-4A1F-8C15-7178938D33AD",
				"type": "Mesh",
				"name": "P16_1_1",
				"userData": {
					"transformData": {
						"inheritType": 1,
						"eulerOrder": "ZYX",
						"translation": [-49.5,9.022255,-0.560333],
						"rotation": [180,0,90],
						"scale": [7,7,7],
						"parentMatrixWorld": {
							"elements": [1,0,0,0,0,1,0,0,0,0,1,0,0,0,0,1]
						}
					}
				},
				"layers": 1,
				"matrix": [0,7,0,0,7,0,0,0,0,0,-7,0,-49.5,9.022255,-0.560333,1],
				"geometry": "3DE3B7E5-4401-4338-9048-1BD5D4A58D07",
				"material": "F8D6A31D-3EB2-41D7-92DC-8AA39212903D"
			},
			{
				"uuid": "C45488B7-F95C-4A66-A036-77A11A18CFCA",
				"type": "Mesh",
				"name": "P13_1_1",
				"userData": {
					"transformData": {
						"inheritType": 1,
						"eulerOrder": "ZYX",
						"translation": [-49.5,17.860181,-10.270271],
						"rotation": [180,0,90],
						"scale": [7,7,7],
						"parentMatrixWorld": {
							"elements": [1,0,0,0,0,1,0,0,0,0,1,0,0,0,0,1]
						}
					}
				},
				"layers": 1,
				"matrix": [0,7,0,0,7,0,0,0,0,0,-7,0,-49.5,17.860181,-10.270271,1],
				"geometry": "064DC351-D301-40BC-B3FC-87B7076A3808",
				"material": "F8D6A31D-3EB2-41D7-92DC-8AA39212903D"
			},
			{
				"uuid": "8B3A132E-C8FA-4580-BDF3-8650F6E3812B",
				"type": "Mesh",
				"name": "P14_1_1",
				"userData": {
					"transformData": {
						"inheritType": 1,
						"eulerOrder": "ZYX",
						"translation": [-49.5,18.146041,-19.644419],
						"rotation": [180,0,90],
						"scale": [7,7,7],
						"parentMatrixWorld": {
							"elements": [1,0,0,0,0,1,0,0,0,0,1,0,0,0,0,1]
						}
					}
				},
				"layers": 1,
				"matrix": [0,7,0,0,7,0,0,0,0,0,-7,0,-49.5,18.146041,-19.644419,1],
				"geometry": "878BBC7B-B28D-4AAA-8F98-93B90EEEAE14",
				"material": "F8D6A31D-3EB2-41D7-92DC-8AA39212903D"
			},
			{
				"uuid": "6A17B4CE-A3F1-4137-9669-C6528B643F20",
				"type": "Mesh",
				"name": "P17_1_1",
				"userData": {
					"transformData": {
						"inheritType": 1,
						"eulerOrder": "ZYX",
						"translation": [-49.700905,8.863596,-24.292871],
						"rotation": [180,0,90],
						"scale": [7,7,7],
						"parentMatrixWorld": {
							"elements": [1,0,0,0,0,1,0,0,0,0,1,0,0,0,0,1]
						}
					}
				},
				"layers": 1,
				"matrix": [0,7,0,0,7,0,0,0,0,0,-7,0,-49.700905,8.863596,-24.292871,1],
				"geometry": "76286D96-ABD7-4057-A18C-129062CDF376",
				"material": "F8D6A31D-3EB2-41D7-92DC-8AA39212903D"
			},
			{
				"uuid": "970FB6BE-1F8E-418E-961D-88BBA14717E4",
				"type": "Mesh",
				"name": "P18_1_1",
				"userData": {
					"transformData": {
						"inheritType": 1,
						"eulerOrder": "ZYX",
						"translation": [-49.664087,9.096318,-33.921827],
						"rotation": [180,0,90],
						"scale": [7,7,7],
						"parentMatrixWorld": {
							"elements": [1,0,0,0,0,1,0,0,0,0,1,0,0,0,0,1]
						}
					}
				},
				"layers": 1,
				"matrix": [0,7,0,0,7,0,0,0,0,0,-7,0,-49.664087,9.096318,-33.921827,1],
				"geometry": "1D4616E8-30C0-4586-AB7C-F93BF0DA76C5",
				"material": "F8D6A31D-3EB2-41D7-92DC-8AA39212903D"
			},
			{
				"uuid": "DF07AAAF-1334-4941-84B8-B3EC2569123E",
				"type": "Mesh",
				"name": "P21_1_1",
				"userData": {
					"transformData": {
						"inheritType": 1,
						"eulerOrder": "ZYX",
						"translation": [-49.91463,-0.244276,0.987418],
						"rotation": [180,0,90],
						"scale": [7,7,7],
						"parentMatrixWorld": {
							"elements": [1,0,0,0,0,1,0,0,0,0,1,0,0,0,0,1]
						}
					}
				},
				"layers": 1,
				"matrix": [0,7,0,0,7,0,0,0,0,0,-7,0,-49.91463,-0.244276,0.987418,1],
				"geometry": "59BC89D3-957F-44DC-88B3-20AB07DD08F3",
				"material": "F8D6A31D-3EB2-41D7-92DC-8AA39212903D"
			},
			{
				"uuid": "32E52A4B-1562-447E-83F1-7A979B31FC24",
				"type": "Mesh",
				"name": "P22_1_1",
				"userData": {
					"transformData": {
						"inheritType": 1,
						"eulerOrder": "ZYX",
						"translation": [-49.740348,-3.30581,-6.471911],
						"rotation": [180,0,90],
						"scale": [7,7,7],
						"parentMatrixWorld": {
							"elements": [1,0,0,0,0,1,0,0,0,0,1,0,0,0,0,1]
						}
					}
				},
				"layers": 1,
				"matrix": [0,7,0,0,7,0,0,0,0,0,-7,0,-49.740348,-3.30581,-6.471911,1],
				"geometry": "AB1EE80D-94BD-4534-9F30-F376258B6DD1",
				"material": "F8D6A31D-3EB2-41D7-92DC-8AA39212903D"
			},
			{
				"uuid": "EA202FC6-83A1-4A23-A0A3-BE7585959E95",
				"type": "Mesh",
				"name": "P23_1_1",
				"userData": {
					"transformData": {
						"inheritType": 1,
						"eulerOrder": "ZYX",
						"translation": [-49.810186,-6.472187,-14.302555],
						"rotation": [180,0,90],
						"scale": [7,7,7],
						"parentMatrixWorld": {
							"elements": [1,0,0,0,0,1,0,0,0,0,1,0,0,0,0,1]
						}
					}
				},
				"layers": 1,
				"matrix": [0,7,0,0,7,0,0,0,0,0,-7,0,-49.810186,-6.472187,-14.302555,1],
				"geometry": "BEA11C78-1C8B-4C27-90E2-8157A8EADF24",
				"material": "F8D6A31D-3EB2-41D7-92DC-8AA39212903D"
			},
			{
				"uuid": "1A1C93ED-EA18-430D-A788-4693E35BB76F",
				"type": "Mesh",
				"name": "P20_1_1",
				"userData": {
					"transformData": {
						"inheritType": 1,
						"eulerOrder": "ZYX",
						"translation": [-49.750988,-2.928882,8.650484],
						"rotation": [180,0,90],
						"scale": [7,7,7],
						"parentMatrixWorld": {
							"elements": [1,0,0,0,0,1,0,0,0,0,1,0,0,0,0,1]
						}
					}
				},
				"layers": 1,
				"matrix": [0,7,0,0,7,0,0,0,0,0,-7,0,-49.750988,-2.928882,8.650484,1],
				"geometry": "6557BDC1-B29C-488F-8FB7-574998B6FE8A",
				"material": "F8D6A31D-3EB2-41D7-92DC-8AA39212903D"
			},
			{
				"uuid": "7227D745-982F-4BE6-B469-F7796437642D",
				"type": "Mesh",
				"name": "P19_1_1",
				"userData": {
					"transformData": {
						"inheritType": 1,
						"eulerOrder": "ZYX",
						"translation": [-49.783104,-5.282414,15.82894],
						"rotation": [180,0,90],
						"scale": [7,7,7],
						"parentMatrixWorld": {
							"elements": [1,0,0,0,0,1,0,0,0,0,1,0,0,0,0,1]
						}
					}
				},
				"layers": 1,
				"matrix": [0,7,0,0,7,0,0,0,0,0,-7,0,-49.783104,-5.282414,15.82894,1],
				"geometry": "52CE19EA-A2C1-47B1-9D7B-B3B4A6B7C2D6",
				"material": "F8D6A31D-3EB2-41D7-92DC-8AA39212903D"
			},
			{
				"uuid": "BFD84C0B-5646-450D-AE9E-0811582C2B30",
				"type": "Mesh",
				"name": "P24_1_1",
				"userData": {
					"transformData": {
						"inheritType": 1,
						"eulerOrder": "ZYX",
						"translation": [-46.221138,-20.136119,-38.45647],
						"rotation": [143.253233,0,90],
						"scale": [10,10,10],
						"parentMatrixWorld": {
							"elements": [1,0,0,0,0,1,0,0,0,0,1,0,0,0,0,1]
						}
					}
				},
				"layers": 1,
				"matrix": [0,10,0,0,8.012876,0,5.982794,0,5.982794,0,-8.012876,0,-46.221138,-20.136119,-38.45647,1],
				"geometry": "1EA0326D-DE1A-41D4-B7DB-76659B565EFF",
				"material": "F8D6A31D-3EB2-41D7-92DC-8AA39212903D"
			},
			{
				"uuid": "67C4BE12-1AE1-4BAF-99C4-9EB17ED20921",
				"type": "Mesh",
				"name": "P25_1_1",
				"userData": {
					"transformData": {
						"inheritType": 1,
						"eulerOrder": "ZYX",
						"translation": [-23.781295,-12.616687,-44.640832],
						"rotation": [117.527752,0,90],
						"scale": [10,10,10],
						"parentMatrixWorld": {
							"elements": [1,0,0,0,0,1,0,0,0,0,1,0,0,0,0,1]
						}
					}
				},
				"layers": 1,
				"matrix": [0,10,0,0,4.621782,0,8.867871,0,8.867871,0,-4.621782,0,-23.781295,-12.616687,-44.640832,1],
				"geometry": "8ABB8F5F-CC64-46C6-AA47-056C3D4AE4B5",
				"material": "F8D6A31D-3EB2-41D7-92DC-8AA39212903D"
			},
			{
				"uuid": "C46A6FF2-D87D-463F-834D-EA0C6D192E85",
				"type": "Mesh",
				"name": "P26_1_1",
				"userData": {
					"transformData": {
						"inheritType": 1,
						"eulerOrder": "ZYX",
						"translation": [33.759485,-5.9389,-49.830794],
						"rotation": [89.697739,-0.145271,91.367904],
						"scale": [10,10,10],
						"parentMatrixWorld": {
							"elements": [1,0,0,0,0,1,0,0,0,0,1,0,0,0,0,1]
						}
					}
				},
				"layers": 1,
				"matrix": [-0.238721,9.997118,0.025355,0,-0.052134,-0.026606,9.999829,0,9.997014,0.238585,0.052754,0,33.759485,-5.9389,-49.830794,1],
				"geometry": "520253F0-59B7-4FE8-A5E0-082A2275D153",
				"material": "F8D6A31D-3EB2-41D7-92DC-8AA39212903D"
			},
			{
				"uuid": "9514CCC2-73AC-4DB5-938E-4002B259E16E",
				"type": "Mesh",
				"name": "P27_1_1",
				"userData": {
					"transformData": {
						"inheritType": 1,
						"eulerOrder": "ZYX",
						"translation": [46.465797,-6.200414,-49.883461],
						"rotation": [89.697739,-0.145271,91.367904],
						"scale": [10,10,10],
						"parentMatrixWorld": {
							"elements": [1,0,0,0,0,1,0,0,0,0,1,0,0,0,0,1]
						}
					}
				},
				"layers": 1,
				"matrix": [-0.238721,9.997118,0.025355,0,-0.052134,-0.026606,9.999829,0,9.997014,0.238585,0.052754,0,46.465797,-6.200414,-49.883461,1],
				"geometry": "BEF29026-6676-4546-8AA4-A405A06D9A93",
				"material": "F8D6A31D-3EB2-41D7-92DC-8AA39212903D"
			},
			{
				"uuid": "084F2AE8-EEEB-4871-9133-FD31BC45C49E",
				"type": "Mesh",
				"name": "P28_1_1",
				"userData": {
					"transformData": {
						"inheritType": 1,
						"eulerOrder": "ZYX",
						"translation": [49.703957,-5.742815,-41.858539],
						"rotation": [0,-0.145271,91.367904],
						"scale": [10,10,10],
						"parentMatrixWorld": {
							"elements": [1,0,0,0,0,1,0,0,0,0,1,0,0,0,0,1]
						}
					}
				},
				"layers": 1,
				"matrix": [-0.238721,9.997118,0.025355,0,-9.99715,-0.238722,0,0,0.000605,-0.025347,9.999968,0,49.703957,-5.742815,-41.858539,1],
				"geometry": "1D55D218-C339-4569-ABE6-7C24DB290FA3",
				"material": "F8D6A31D-3EB2-41D7-92DC-8AA39212903D"
			},
			{
				"uuid": "0FDA2FA7-1162-4731-8A09-4B1315040C29",
				"type": "Mesh",
				"name": "P29_1_1",
				"userData": {
					"transformData": {
						"inheritType": 1,
						"eulerOrder": "ZYX",
						"translation": [49.9,12.3329,-8.153405],
						"rotation": [180,0,-90],
						"scale": [4.5,4.5,4.5],
						"parentMatrixWorld": {
							"elements": [1,0,0,0,0,1,0,0,0,0,1,0,0,0,0,1]
						}
					}
				},
				"layers": 1,
				"matrix": [0,4.5,0,0,-4.5,0,0,0,0,0,4.5,0,49.9,12.3329,-8.153405,1],
				"geometry": "F632F3FC-1146-4B57-A804-7CDF5A6E08A5",
				"material": "F8D6A31D-3EB2-41D7-92DC-8AA39212903D"
			},
			{
				"uuid": "E71906CE-AA48-4EB2-89DF-929864C13898",
				"type": "Mesh",
				"name": "P30_1_1",
				"userData": {
					"transformData": {
						"inheritType": 1,
						"eulerOrder": "ZYX",
						"translation": [49.9,12.475674,-1.501137],
						"rotation": [180,0,-90],
						"scale": [4.5,4.5,4.5],
						"parentMatrixWorld": {
							"elements": [1,0,0,0,0,1,0,0,0,0,1,0,0,0,0,1]
						}
					}
				},
				"layers": 1,
				"matrix": [0,4.5,0,0,-4.5,0,0,0,0,0,4.5,0,49.9,12.475674,-1.501137,1],
				"geometry": "03FF56F8-D813-46B1-ACCA-4E1F253EFDBD",
				"material": "F8D6A31D-3EB2-41D7-92DC-8AA39212903D"
			},
			{
				"uuid": "E0423A70-D106-4481-BDB0-32EE843B78AD",
				"type": "Mesh",
				"name": "P31_1_1",
				"userData": {
					"transformData": {
						"inheritType": 1,
						"eulerOrder": "ZYX",
						"translation": [49.9,7.411395,-8.376408],
						"rotation": [180,0,-90],
						"scale": [4,4,4],
						"parentMatrixWorld": {
							"elements": [1,0,0,0,0,1,0,0,0,0,1,0,0,0,0,1]
						}
					}
				},
				"layers": 1,
				"matrix": [0,4,0,0,-4,0,0,0,0,0,4,0,49.9,7.411395,-8.376408,1],
				"geometry": "C14FBD43-04C8-45FC-BE52-B6E01AF22A11",
				"material": "F8D6A31D-3EB2-41D7-92DC-8AA39212903D"
			},
			{
				"uuid": "1D96AC4D-D731-4A0B-8072-FD6691DAC724",
				"type": "Mesh",
				"name": "P32_1_1",
				"userData": {
					"transformData": {
						"inheritType": 1,
						"eulerOrder": "ZYX",
						"translation": [49.9,3.791928,-3.289812],
						"rotation": [180,0,-90],
						"scale": [4.5,4.5,4.5],
						"parentMatrixWorld": {
							"elements": [1,0,0,0,0,1,0,0,0,0,1,0,0,0,0,1]
						}
					}
				},
				"layers": 1,
				"matrix": [0,4.5,0,0,-4.5,0,0,0,0,0,4.5,0,49.9,3.791928,-3.289812,1],
				"geometry": "B4F1E32B-815F-41FB-AD07-B34673E3BD04",
				"material": "F8D6A31D-3EB2-41D7-92DC-8AA39212903D"
			},
			{
				"uuid": "009A1D42-69C7-4AD3-9C83-A53FA4676F3E",
				"type": "Mesh",
				"name": "P34_1_1",
				"userData": {
					"transformData": {
						"inheritType": 1,
						"eulerOrder": "ZYX",
						"translation": [49.900001,-3.00622,-0.905375],
						"rotation": [180,0,-90],
						"scale": [4.5,4.5,4.5],
						"parentMatrixWorld": {
							"elements": [1,0,0,0,0,1,0,0,0,0,1,0,0,0,0,1]
						}
					}
				},
				"layers": 1,
				"matrix": [0,4.5,0,0,-4.5,0,0,0,0,0,4.5,0,49.900001,-3.00622,-0.905375,1],
				"geometry": "4ACB72E7-2C92-4CF5-BC9C-434CEF6D4A41",
				"material": "F8D6A31D-3EB2-41D7-92DC-8AA39212903D"
			},
			{
				"uuid": "264F8592-695D-4818-9213-9263FA09F086",
				"type": "Mesh",
				"name": "P33_1_1",
				"userData": {
					"transformData": {
						"inheritType": 1,
						"eulerOrder": "ZYX",
						"translation": [49.9,-5.313849,-5.681847],
						"rotation": [180,0,-90],
						"scale": [4.5,4.5,4.5],
						"parentMatrixWorld": {
							"elements": [1,0,0,0,0,1,0,0,0,0,1,0,0,0,0,1]
						}
					}
				},
				"layers": 1,
				"matrix": [0,4.5,0,0,-4.5,0,0,0,0,0,4.5,0,49.9,-5.313849,-5.681847,1],
				"geometry": "5C7F77A3-869D-4521-A2D0-4093DF273142",
				"material": "F8D6A31D-3EB2-41D7-92DC-8AA39212903D"
			},
			{
				"uuid": "D6F9050E-C575-466A-92E2-844DF7945C5C",
				"type": "Mesh",
				"name": "P35_1_1",
				"userData": {
					"transformData": {
						"inheritType": 1,
						"eulerOrder": "ZYX",
						"translation": [49.9,-4.44813,4.513625],
						"rotation": [180,0,-90],
						"scale": [4.5,4.5,4.5],
						"parentMatrixWorld": {
							"elements": [1,0,0,0,0,1,0,0,0,0,1,0,0,0,0,1]
						}
					}
				},
				"layers": 1,
				"matrix": [0,4.5,0,0,-4.5,0,0,0,0,0,4.5,0,49.9,-4.44813,4.513625,1],
				"geometry": "AEE13806-3827-4ED8-95E6-1AD4BF8BA6EC",
				"material": "F8D6A31D-3EB2-41D7-92DC-8AA39212903D"
			},
			{
				"uuid": "CEF73BF6-765C-4391-914C-2D6F3E3E10E1",
				"type": "Mesh",
				"name": "A1_2_1",
				"userData": {
					"transformData": {
						"inheritType": 1,
						"eulerOrder": "ZYX",
						"translation": [48.839141,5.547359,20.57216],
						"rotation": [180,0,-90],
						"scale": [10,10,20],
						"parentMatrixWorld": {
							"elements": [1,0,0,0,0,1,0,0,0,0,1,0,0,0,0,1]
						}
					}
				},
				"layers": 1,
				"matrix": [0,10,0,0,-10,0,0,0,0,0,20,0,48.839141,5.547359,20.57216,1],
				"geometry": "BE0F31E7-B9F1-43D6-9C6A-157F1124B0A0",
				"material": "F8D6A31D-3EB2-41D7-92DC-8AA39212903D"
			},
			{
				"uuid": "A9F5EB5A-14A6-4EB1-834A-4C89A0C105E8",
				"type": "Mesh",
				"name": "A2_2_1",
				"userData": {
					"transformData": {
						"inheritType": 1,
						"eulerOrder": "ZYX",
						"translation": [26.006759,4.295974,49.856412],
						"rotation": [-90,0,90],
						"scale": [6,6,12],
						"parentMatrixWorld": {
							"elements": [1,0,0,0,0,1,0,0,0,0,1,0,0,0,0,1]
						}
					}
				},
				"layers": 1,
				"matrix": [0,6,0,0,0,0,-6,0,-12,0,0,0,26.006759,4.295974,49.856412,1],
				"geometry": "0C5F3259-BBEB-4124-A5E4-D30F960174E0",
				"material": "F8D6A31D-3EB2-41D7-92DC-8AA39212903D"
			},
			{
				"uuid": "DAA02B0C-B456-4BBE-A513-3520956CC8D5",
				"type": "Mesh",
				"name": "A3_2_1",
				"userData": {
					"transformData": {
						"inheritType": 1,
						"eulerOrder": "ZYX",
						"translation": [3.783554,4.405063,49.856412],
						"rotation": [-90,0,90],
						"scale": [8,8,16],
						"parentMatrixWorld": {
							"elements": [1,0,0,0,0,1,0,0,0,0,1,0,0,0,0,1]
						}
					}
				},
				"layers": 1,
				"matrix": [0,8,0,0,0,0,-8,0,-16,0,0,0,3.783554,4.405063,49.856412,1],
				"geometry": "1CC10461-5B56-4B69-AAD5-A67EE97F27E2",
				"material": "F8D6A31D-3EB2-41D7-92DC-8AA39212903D"
			},
			{
				"uuid": "82CC60B4-F71D-4F9A-B976-EF12894CC7CD",
				"type": "Mesh",
				"name": "A4_2_1",
				"userData": {
					"transformData": {
						"inheritType": 1,
						"eulerOrder": "ZYX",
						"translation": [-14.041839,4.405063,49.856412],
						"rotation": [-90,0,90],
						"scale": [8,8,16],
						"parentMatrixWorld": {
							"elements": [1,0,0,0,0,1,0,0,0,0,1,0,0,0,0,1]
						}
					}
				},
				"layers": 1,
				"matrix": [0,8,0,0,0,0,-8,0,-16,0,0,0,-14.041839,4.405063,49.856412,1],
				"geometry": "E2F043ED-F275-41F6-B0FE-B5637A173E28",
				"material": "F8D6A31D-3EB2-41D7-92DC-8AA39212903D"
			},
			{
				"uuid": "ABFA3189-7CF8-467A-9124-77BBF6A3B53A",
				"type": "Mesh",
				"name": "A5_2_1",
				"userData": {
					"transformData": {
						"inheritType": 1,
						"eulerOrder": "ZYX",
						"translation": [-4.712517,9.794073,-49.747101],
						"rotation": [89.697739,-0.145271,91.367904],
						"scale": [15,15,30],
						"parentMatrixWorld": {
							"elements": [1,0,0,0,0,1,0,0,0,0,1,0,0,0,0,1]
						}
					}
				},
				"layers": 1,
				"matrix": [-0.358081,14.995677,0.038032,0,-0.078201,-0.039909,14.999743,0,29.991043,0.715754,0.158262,0,-4.712517,9.794073,-49.747101,1],
				"geometry": "283F13DF-126D-4A7E-9DE6-78EE1668A19B",
				"material": "F8D6A31D-3EB2-41D7-92DC-8AA39212903D"
			},
			{
				"uuid": "8E91EE46-8406-403E-A731-DC8B430AD894",
				"type": "Mesh",
				"name": "A6_3_1",
				"userData": {
					"transformData": {
						"inheritType": 1,
						"eulerOrder": "ZYX",
						"translation": [50.476284,10.589285,-49.747101],
						"rotation": [89.697739,-0.145271,91.367904],
						"scale": [15,15,45],
						"parentMatrixWorld": {
							"elements": [1,0,0,0,0,1,0,0,0,0,1,0,0,0,0,1]
						}
					}
				},
				"layers": 1,
				"matrix": [-0.358081,14.995677,0.038032,0,-0.078201,-0.039909,14.999743,0,44.986564,1.073631,0.237393,0,50.476284,10.589285,-49.747101,1],
				"geometry": "3B461168-4D5D-4E54-8FB9-40FB3A9073B2",
				"material": "F8D6A31D-3EB2-41D7-92DC-8AA39212903D"
			}]
	}
}